x64dbg_automate/__init__.py
x64dbg_automate/client_base.py
x64dbg_automate/commands_xauto.py
x64dbg_automate/events.py
x64dbg_automate/hla_xauto.py
x64dbg_automate/models.py
x64dbg_automate/win32.py
x64dbg_automate-0.6.2.dist-info/licenses/LICENSE
x64dbg_automate-0.6.2.dist-info/METADATA
x64dbg_automate-0.6.2.dist-info/WHEEL
x64dbg_automate-0.6.2.dist-info/RECORD
