Metadata-Version: 2.4
Name: x64dbg_automate
Version: 0.6.2
Summary: A Python library to automate x64dbg
License-File: LICENSE
Keywords: x64dbg,debugger,instrumentation,plugin,dynamic-analysis
Author: Darius Houle
Author-email: darius@x64.ooo
Requires-Python: >=3.10,<4.0
Classifier: Programming Language :: Python :: 3
Classifier: Programming Language :: Python :: 3.10
Classifier: Programming Language :: Python :: 3.11
Classifier: Programming Language :: Python :: 3.12
Classifier: Programming Language :: Python :: 3.13
Classifier: Programming Language :: Python :: 3.14
Requires-Dist: msgpack (>=1.1.0,<2.0.0)
Requires-Dist: psutil (>=6.1.1,<7.0.0)
Requires-Dist: pydantic (>=2.10.6,<3.0.0)
Requires-Dist: pyzmq (>=26.2.0,<27.0.0)
Project-URL: Homepage, https://dariushoule.github.io/x64dbg-automate-pyclient/
Project-URL: Issues, https://github.com/dariushoule/x64dbg-automate-pyclient/issues
Project-URL: Repository, https://github.com/dariushoule/x64dbg-automate-pyclient
